mr_piper-0.1.10.dist-info/DESCRIPTION.rst
mr_piper-0.1.10.dist-info/METADATA
mr_piper-0.1.10.dist-info/RECORD
mr_piper-0.1.10.dist-info/WHEEL
mr_piper-0.1.10.dist-info/entry_points.txt
mr_piper-0.1.10.dist-info/metadata.json
mr_piper-0.1.10.dist-info/top_level.txt
mrpiper/__init__.py
mrpiper/cli.py
mrpiper/environments.py
mrpiper/overrides.py
mrpiper/piper.py
mrpiper/piper_json.py
mrpiper/project.py
mrpiper/pyenv_utils.py
mrpiper/utils.py
mrpiper/templates/setup.py.template
mrpiper/vendor/__init__.py
mrpiper/vendor/hashin.py
mrpiper/vendor/pipdeptree.py
mrpiper/vendor/requirements/__init__.py
mrpiper/vendor/requirements/parser.py
mrpiper/vendor/requirements/requirement.py
mrpiper/vendor/requirements/vcs.py
tests/__init__.py
tests/test_cli.py
tests/test_piper.py
