Metadata-Version: 2.0
Name: mr-piper
Version: 0.1.10
Summary: The simple project package manager
Home-page: https://github.com/jamespacileo/mr-piper
Author: James Pacileo
Author-email: UNKNOWN
License: MIT
Keywords: p,i,p, ,p,i,p,e,r, ,m,r,p,i,p,e,r, ,p,a,c,k,a,g,e, ,m,a,n,a,g,e,r
Platform: UNKNOWN
Classifier: License :: OSI Approved :: MIT License
Classifier: Programming Language :: Python
Classifier: Programming Language :: Python :: 2.7
Classifier: Programming Language :: Python :: 3
Classifier: Programming Language :: Python :: 3.3
Classifier: Programming Language :: Python :: 3.4
Classifier: Programming Language :: Python :: 3.5
Classifier: Programming Language :: Python :: 3.6
Classifier: Programming Language :: Python :: Implementation :: CPython
Classifier: Programming Language :: Python :: Implementation :: PyPy
Requires-Dist: click (>=6.7)
Requires-Dist: click-log (>=0.2.0)
Requires-Dist: click-spinner (>=0.1.7)
Requires-Dist: crayons (>=0.1.2)
Requires-Dist: delegator.py (>=0.0.13)
Requires-Dist: emoji (>=0.4.5)
Requires-Dist: future (>=0.16.0)
Requires-Dist: parse (>=1.8.2)
Requires-Dist: path.py (>=10.4)
Requires-Dist: requests (>=2.0.0)
Requires-Dist: semantic-version (>=2.6.0)
Requires-Dist: simplejson (>=3.11.1)
Requires-Dist: tabulate (>=0.7.7)
